bharat_pii/__init__.py
bharat_pii/api.py
bharat_pii/entities.py
bharat_pii/utils.py
bharat_pii/validators.py
bharat_pii/detectors/__init__.py
bharat_pii/detectors/aadhaar.py
bharat_pii/detectors/base.py
bharat_pii/detectors/credit_card.py
bharat_pii/detectors/ifsc.py
bharat_pii/detectors/pan.py
bharat_pii/detectors/phone.py
bharat_pii/detectors/upi.py
bharat_pii/redaction/__init__.py
bharat_pii/redaction/masker.py
bharat_pii-0.1.2.dist-info/licenses/LICENSE
bharat_pii-0.1.2.dist-info/METADATA
bharat_pii-0.1.2.dist-info/WHEEL
bharat_pii-0.1.2.dist-info/top_level.txt
bharat_pii-0.1.2.dist-info/RECORD
