Metadata-Version: 2.4
Name: bharat-pii
Version: 0.1.2
Summary: India-first PII detection & redaction library
Author: Rahul Sharma
License: MIT License
Classifier: Programming Language :: Python :: 3
Classifier: Programming Language :: Python :: 3.10
Classifier: Programming Language :: Python :: 3.11
Classifier: Programming Language :: Python :: 3.12
Classifier: License :: OSI Approved :: MIT License
Classifier: Operating System :: OS Independent
Requires-Python: >=3.10
License-File: LICENSE
Requires-Dist: regex
Dynamic: license-file
